odoo/addons/fs_storage_backup/README.rst
odoo/addons/fs_storage_backup/__init__.py
odoo/addons/fs_storage_backup/__manifest__.py
odoo/addons/fs_storage_backup/data/ir_cron_data.xml
odoo/addons/fs_storage_backup/data/mail_message_subtype_data.xml
odoo/addons/fs_storage_backup/i18n/fs_storage_backup.pot
odoo/addons/fs_storage_backup/i18n/it.po
odoo/addons/fs_storage_backup/models/__init__.py
odoo/addons/fs_storage_backup/models/fs_storage.py
odoo/addons/fs_storage_backup/readme/CONFIGURE.md
odoo/addons/fs_storage_backup/readme/CONTRIBUTORS.md
odoo/addons/fs_storage_backup/readme/DESCRIPTION.md
odoo/addons/fs_storage_backup/readme/ROADMAP.md
odoo/addons/fs_storage_backup/readme/USAGE.md
odoo/addons/fs_storage_backup/static/description/icon.png
odoo/addons/fs_storage_backup/static/description/index.html
odoo/addons/fs_storage_backup/tests/__init__.py
odoo/addons/fs_storage_backup/tests/test_backup.py
odoo/addons/fs_storage_backup/views/fs_storage_view.xml
odoo_addon_fs_storage_backup-16.0.1.0.1.3.dist-info/METADATA
odoo_addon_fs_storage_backup-16.0.1.0.1.3.dist-info/WHEEL
odoo_addon_fs_storage_backup-16.0.1.0.1.3.dist-info/top_level.txt
odoo_addon_fs_storage_backup-16.0.1.0.1.3.dist-info/RECORD
