Metadata-Version: 2.1
Name: odoo-addon-fs_storage_backup
Version: 16.0.1.0.1.3
Summary: Filesystem Storage Backup
Home-page: https://github.com/OCA/storage
Author: Onestein, Odoo Community Association (OCA)
Author-email: support@odoo-community.org
License: AGPL-3
Classifier: Programming Language :: Python
Classifier: Framework :: Odoo
Classifier: Framework :: Odoo :: 16.0
Classifier: License :: OSI Approved :: GNU Affero General Public License v3
Requires-Python: >=3.10
Requires-Dist: odoo-addon-fs-storage<16.1dev,>=16.0dev
Requires-Dist: odoo<16.1dev,>=16.0a
